Metadata-Version: 2.1
Name: open3dlite
Version: 0.0.5
Summary: An easy syntax of Python Package Open3d
Home-page: https://github.com/haroon4412/open3d_lite.git
Author: Muhammad Haroon
Author-email: muhammad.haroon44@gmail.com
Classifier: Programming Language :: Python :: 3
Classifier: License :: OSI Approved :: MIT License
Classifier: Operating System :: OS Independent
Requires-Python: >=3.6
License-File: LICENSE
